secret_splitter/__init__.py
secret_splitter/__main__.py
secret_splitter/block_sss.py
secret_splitter/common.py
secret_splitter/secret_splitter.py
secret_splitter-1.8.0.dist-info/METADATA
secret_splitter-1.8.0.dist-info/WHEEL
secret_splitter-1.8.0.dist-info/licenses/LICENSE
secret_splitter-1.8.0.dist-info/RECORD
