Metadata-Version: 2.1
Name: secret-splitter
Version: 1.8.0
Summary: Split secrets into pieces, or attemp to recover secrets by recombining a subset of pieces.
Project-URL: Homepage, https://secret-splitter.com
Project-URL: Source, https://git.sr.ht/~retzoh/secret-splitter-py
Project-URL: Bug Tracker, https://todo.sr.ht/~retzoh/secret-splitter-py
Author-email: Henri Bourdeau <hb@wolfzoh.com>
License: BSD License
License-File: LICENSE
Keywords: cryptography,password,secret,sharing,splitting
Classifier: Development Status :: 6 - Mature
Classifier: License :: OSI Approved :: BSD License
Classifier: Operating System :: OS Independent
Classifier: Programming Language :: Python :: 3
Classifier: Topic :: Security :: Cryptography
Requires-Python: >=3.8
Requires-Dist: pyyaml
